setup.py
book2arrange/__init__.py
book2arrange.egg-info/PKG-INFO
book2arrange.egg-info/SOURCES.txt
book2arrange.egg-info/dependency_links.txt
book2arrange.egg-info/entry_points.txt
book2arrange.egg-info/top_level.txt