Metadata-Version: 1.1
Name: book2arrange
Version: 1.0.1
Summary: Arrange audio files from http://www.50languages.com/ in one convenient collection for better language acquisition.
Home-page: https://github.com/avanov/book2arrange
Author: Maxim Avanov
Author-email: maxim.avanov@gmail.com
License: MIT
Download-URL: https://github.com/avanov/book2arrange
Keywords: cli utils foreign language education
Platform: UNKNOWN
Classifier: Development Status :: 5 - Production/Stable
Classifier: Environment :: Console
Classifier: Intended Audience :: Education
Classifier: Intended Audience :: End Users/Desktop
Classifier: License :: OSI Approved
Classifier: License :: OSI Approved :: MIT License
Classifier: Operating System :: MacOS
Classifier: Operating System :: Microsoft
Classifier: Operating System :: POSIX
Classifier: Programming Language :: Python
Classifier: Programming Language :: Python :: 2.7
Classifier: Programming Language :: Python :: 3
Classifier: Topic :: Education
